sopel_safety/__init__.py
sopel_safety/plugin.py
sopel_safety-0.1.0.dist-info/licenses/COPYING
sopel_safety-0.1.0.dist-info/METADATA
sopel_safety-0.1.0.dist-info/WHEEL
sopel_safety-0.1.0.dist-info/entry_points.txt
sopel_safety-0.1.0.dist-info/top_level.txt
sopel_safety-0.1.0.dist-info/RECORD
