Metadata-Version: 2.4
Name: sopel-safety
Version: 0.1.0
Summary: A Sopel plugin providing alerts about malicious URLs.
Author: Elad Alfassa
Maintainer-email: dgw <dgw@technobabbl.es>
License-Expression: EFL-2.0
Project-URL: Homepage, https://github.com/sopel-irc/sopel-safety
Project-URL: Bug Tracker, https://github.com/sopel-irc/sopel-safety/issues
Keywords: sopel,plugin,bot,irc
Platform: Linux x86, x86-64
Classifier: Intended Audience :: Developers
Classifier: Intended Audience :: System Administrators
Classifier: Topic :: Communications :: Chat :: Internet Relay Chat
Requires-Python: <4,>=3.8
License-File: COPYING
Requires-Dist: sopel>=8.0
Requires-Dist: requests
Dynamic: license-file
